pyCTelebot/__init__.py
pyCTelebot/buildparser.py
pyCTelebot/pyCTelebotBase.py
pyCTelebot/pyCrypto.py
pyCTelebot/pyCryptoCron.py
pyCTelebot/pyCryptoWorker.py
pyCTelebot/pyTelegram.py
pyCTelebot/config/__init__.py
pyCTelebot/config/auth.py
tests/__init__.py
tests/context.py
tests/test_main.py
pyCTelebot-0.0.1.dist-info/LICENSE
pyCTelebot-0.0.1.dist-info/METADATA
pyCTelebot-0.0.1.dist-info/WHEEL
pyCTelebot-0.0.1.dist-info/entry_points.txt
pyCTelebot-0.0.1.dist-info/top_level.txt
pyCTelebot-0.0.1.dist-info/RECORD
