Metadata-Version: 2.1
Name: pyCTelebot
Version: 0.0.1
Summary: pyCTelebot
Home-page: https://github.com/juanjo78git/pyCTelebot
Author: JuanJo78
Author-email: juanjo78@gmail.com
License: UNKNOWN
Platform: UNKNOWN
Classifier: Programming Language :: Python
Classifier: Development Status :: 4 - Beta
Classifier: License :: OSI Approved :: MIT License
Classifier: Operating System :: OS Independent
Classifier: Programming Language :: Python :: 3.8
Classifier: Topic :: Utilities
License-File: LICENSE
